rmq_helper_flowia/__init__.py
rmq_helper_flowia/flowia_rmq.py
rmq_helper_flowia-0.0.3.dist-info/METADATA
rmq_helper_flowia-0.0.3.dist-info/WHEEL
rmq_helper_flowia-0.0.3.dist-info/licenses/LICENSE
rmq_helper_flowia-0.0.3.dist-info/RECORD
